bsblan/__init__.py
bsblan/__version__.py
bsblan/bsblan.py
bsblan/exceptions.py
bsblan/models.py
bsblan-0.5.0.dist-info/LICENSE.md
bsblan-0.5.0.dist-info/METADATA
bsblan-0.5.0.dist-info/WHEEL
bsblan-0.5.0.dist-info/top_level.txt
bsblan-0.5.0.dist-info/RECORD
