Metadata-Version: 2.1
Name: bsblan
Version: 0.5.0
Summary: Asynchronous Python client for BSBLan.
Home-page: https://github.com/liudger/python-bsblan
Author: Willem-Jan van Rootselaaar
Author-email: liudgervr@gmail.com
License: MIT license
Keywords: bsblan,api,async,client
Platform: UNKNOWN
Classifier: Development Status :: 4 - Beta
Classifier: Framework :: AsyncIO
Classifier: Intended Audience :: Developers
Classifier: License :: OSI Approved :: MIT License
Classifier: Natural Language :: English
Classifier: Programming Language :: Python :: 3.8
Classifier: Programming Language :: Python :: 3.9
Classifier: Programming Language :: Python :: 3
Classifier: Topic :: Software Development :: Libraries :: Python Modules
Requires-Dist: aiohttp (>=3.0.0)
Requires-Dist: attrs (>=19.0.0)
Requires-Dist: cattrs
Requires-Dist: yarl
